datacsv/__init__.py
datacsv/datacsv.py
datacsv-0.1.0.dist-info/licenses/LICENSE
datacsv-0.1.0.dist-info/METADATA
datacsv-0.1.0.dist-info/WHEEL
datacsv-0.1.0.dist-info/top_level.txt
datacsv-0.1.0.dist-info/RECORD
