Metadata-Version: 2.4
Name: datacsv
Version: 0.1.0
Summary: A lightweight CSV database for Python.
Author-email: Mahesh <maheshvish777@gmail.com>
License-Expression: MIT
Project-URL: Homepage, https://github.com/mvish77/datacsv
Project-URL: Issues, https://github.com/mvish77/datacsv/issue
Requires-Python: >=3.7
License-File: LICENSE
Dynamic: license-file
